LICENSE
airflow_metrics_gbq/__init__.py
airflow_metrics_gbq/exceptions.py
airflow_metrics_gbq/metrics.py
airflow_metrics_gbq/utils/__init__.py
airflow_metrics_gbq/utils/gbq_connector.py
airflow_metrics_gbq-0.1.0.dist-info/LICENSE
airflow_metrics_gbq-0.1.0.dist-info/METADATA
airflow_metrics_gbq-0.1.0.dist-info/WHEEL
airflow_metrics_gbq-0.1.0.dist-info/RECORD
