Metadata-Version: 2.1
Name: airflow-metrics-gbq
Version: 0.1.0
Summary: Airflow metrics to Google BigQuery
Home-page: https://github.com/abyssnlp/airflow-metrics-gbq
License: BSD2
Author: Shaurya Rawat
Author-email: rawatshaurya1994@gmail.com
Requires-Python: >=3.8.1,<4.0.0
Classifier: Development Status :: 3 - Alpha
Classifier: Environment :: Console
Classifier: Framework :: Apache Airflow
Classifier: Intended Audience :: Developers
Classifier: License :: OSI Approved :: BSD License
Classifier: License :: Other/Proprietary License
Classifier: Operating System :: OS Independent
Classifier: Programming Language :: Python :: 3
Classifier: Programming Language :: Python :: 3.9
Classifier: Programming Language :: Python :: 3.10
Classifier: Programming Language :: Python :: 3.11
Classifier: Topic :: Software Development :: Libraries :: Python Modules
Requires-Dist: google-api-python-client (>=2.85.0,<3.0.0)
Requires-Dist: google-cloud-bigquery[pandas] (>=3.10.0,<4.0.0)
Requires-Dist: google-cloud-logging (>=3.5.0,<4.0.0)
Requires-Dist: pandas (>=2.0.0,<3.0.0)
Requires-Dist: tenacity (>=8.2.2,<9.0.0)
Project-URL: Repository, https://github.com/abyssnlp/airflow-metrics-gbq
